cachext/__init__.py
cachext/backends.py
cachext/cache.py
cachext/exts.py
cachext-1.2.1.dist-info/LICENSE
cachext-1.2.1.dist-info/METADATA
cachext-1.2.1.dist-info/WHEEL
cachext-1.2.1.dist-info/top_level.txt
cachext-1.2.1.dist-info/RECORD
