Metadata-Version: 2.1
Name: cachext
Version: 1.2.1
Summary: cache extension for sea/flask
Home-page: https://github.com/shanbay/cachext
Author: Michael Ding
Author-email: yandy.ding@gmail.com
License: MIT
Keywords: cache,flask,sea
Classifier: Development Status :: 1 - Planning
Classifier: Environment :: Web Environment
Classifier: Intended Audience :: Developers
Classifier: Operating System :: POSIX
Classifier: License :: OSI Approved :: MIT License
Classifier: Programming Language :: Python
Classifier: Programming Language :: Python :: 3
Classifier: Programming Language :: Python :: 3.4
Classifier: Programming Language :: Python :: 3.5
Classifier: Programming Language :: Python :: 3.6
Classifier: Topic :: Internet
Classifier: Topic :: Software Development :: Libraries :: Python Modules
Requires-Python: >=3
License-File: LICENSE
Requires-Dist: opentelemetry.instrumentation.redis
